mz_project_gender/__init__.py
mz_project_gender/models/__init__.py
mz_project_gender/models/mz_gender_nv_model.pkl
mz_project_gender/models/mz_gender_vectorizer.pkl
mz_project_gender/mz_genclf.py
mz_project_gender-0.1.0.dist-info/WHEEL
mz_project_gender-0.1.0.dist-info/METADATA
mz_project_gender-0.1.0.dist-info/RECORD
